aiohere/__init__.py
aiohere/aiohere.py
aiohere/exceptions.py
aiohere/model/astronomy.py
aiohere/model/daily.py
aiohere/model/daily_simple.py
aiohere/model/hourly.py
aiohere/model/observation.py
aiohere/model/place.py
aiohere/model/product_types.py
aiohere/model/response.py
aiohere/py.typed
aiohere-2.2.0.dist-info/LICENSE
aiohere-2.2.0.dist-info/METADATA
aiohere-2.2.0.dist-info/WHEEL
aiohere-2.2.0.dist-info/RECORD
