Metadata-Version: 2.1
Name: aiohere
Version: 2.2.0
Summary: Asynchronous Python client for the HERE API
Home-page: http://github.com/eifinger/aiohere
License: MIT
Keywords: aiohttp,asyncio,here
Author: Kevin Stillhammer
Author-email: kevin.stillhammer@gmail.com
Requires-Python: >=3.9
Classifier: Intended Audience :: Developers
Classifier: License :: OSI Approved :: MIT License
Classifier: Operating System :: OS Independent
Classifier: Programming Language :: Python
Classifier: Programming Language :: Python :: 3
Classifier: Programming Language :: Python :: 3.9
Classifier: Programming Language :: Python :: 3.10
Classifier: Programming Language :: Python :: 3.11
Classifier: Programming Language :: Python :: 3
Classifier: Topic :: Software Development :: Libraries :: Python Modules
Requires-Dist: aiohttp (>=3.8.3,<4.0.0)
Project-URL: Repository, http://github.com/eifinger/aiohere
